i_mongodb/__init__.py
i_mongodb/i_mongodb.py
i_mongodb/logging_config.json
i_mongodb-2.2.0.dist-info/LICENSE
i_mongodb-2.2.0.dist-info/METADATA
i_mongodb-2.2.0.dist-info/WHEEL
i_mongodb-2.2.0.dist-info/RECORD
