Metadata-Version: 2.1
Name: i-mongodb
Version: 2.2.0
Summary: Customized connector to MongoDB
Home-page: https://github.com/aracnid/i-mongodb
License: MIT
Keywords: python,mongodb
Author: Jason Romano
Author-email: aracnid@gmail.com
Requires-Python: >=3.10,<4.0
Classifier: License :: OSI Approved :: MIT License
Classifier: Programming Language :: Python :: 3
Classifier: Programming Language :: Python :: 3.10
Classifier: Programming Language :: Python :: 3.11
Classifier: Programming Language :: Python :: 3.12
Classifier: Programming Language :: Python :: 3.13
Requires-Dist: aracnid_logger (>=1.0,<2.0)
Requires-Dist: dnspython (>=1.16,<2.0)
Requires-Dist: pymongo[srv] (>=4.10,<5.0)
Requires-Dist: python-dateutil (>=2.8,<3.0)
Project-URL: Repository, https://github.com/aracnid/i-mongodb
